automation_qa_key_helper/__init__.py
automation_qa_key_helper/helper.py
automation_qa_key_helper/qa_key.json
qa_keys_test-0.0.12.dist-info/LICENSE
qa_keys_test-0.0.12.dist-info/METADATA
qa_keys_test-0.0.12.dist-info/WHEEL
qa_keys_test-0.0.12.dist-info/top_level.txt
qa_keys_test-0.0.12.dist-info/RECORD
