Metadata-Version: 2.1
Name: qa-keys-test
Version: 0.0.12
Summary: A repo is for xhis single source
Home-page: https://github.com/OwenLuo123/qa-tag-test.git
License: UNKNOWN
Platform: UNKNOWN
License-File: LICENSE
